multipykinect_azure/__init__.py
multipykinect_azure/pykinect.py
multipykinect_azure/k4a/__init__.py
multipykinect_azure/k4a/_k4a.py
multipykinect_azure/k4a/_k4atypes.py
multipykinect_azure/k4a/calibration.py
multipykinect_azure/k4a/capture.py
multipykinect_azure/k4a/configuration.py
multipykinect_azure/k4a/device.py
multipykinect_azure/k4a/image.py
multipykinect_azure/k4a/imu_sample.py
multipykinect_azure/k4a/transformation.py
multipykinect_azure/k4abt/__init__.py
multipykinect_azure/k4abt/_k4abt.py
multipykinect_azure/k4abt/_k4abtTypes.py
multipykinect_azure/k4abt/body.py
multipykinect_azure/k4abt/body2d.py
multipykinect_azure/k4abt/frame.py
multipykinect_azure/k4abt/joint.py
multipykinect_azure/k4abt/joint2d.py
multipykinect_azure/k4abt/tracker.py
multipykinect_azure/k4arecord/__init__.py
multipykinect_azure/k4arecord/_k4arecord.py
multipykinect_azure/k4arecord/_k4arecordTypes.py
multipykinect_azure/k4arecord/datablock.py
multipykinect_azure/k4arecord/playback.py
multipykinect_azure/k4arecord/record.py
multipykinect_azure/k4arecord/record_configuration.py
multipykinect_azure/utils/__init__.py
multipykinect_azure/utils/postProcessing.py
multipykinect_azure/utils/utils.py
multipykinect_azure-0.0.1.dist-info/METADATA
multipykinect_azure-0.0.1.dist-info/WHEEL
multipykinect_azure-0.0.1.dist-info/top_level.txt
multipykinect_azure-0.0.1.dist-info/RECORD
