Metadata-Version: 2.1
Name: multipykinect_azure
Version: 0.0.1
Summary: Python library to run Kinect Azure DK SDK functions which support multiple devices
Home-page: https://github.com/MojiCartman/pyKinectAzure
Author: Ibai Gorordo, JiaweiDing
License: MIT
Requires-Dist: numpy
Requires-Dist: opencv-python
